{
  "type":"StackOverflowArtifact",
  "question":{
    "type":"StackOverflowQuestion",
    "id":10210368,
    "title":"How stable is Netty 4?",
    "comments":[
      {
        "type":"StackOverflowComment",
        "id":23754340,
        "postId":10210368,
        "creationDate":"2013-05-14",
        "score":0,
        "isEdited":false,
        "owner":{
          "type":"StackOverflowUser",
          "id":962758,
          "displayName":"Eduardo Bezerra",
          "reputation":601
        },
        "source":[
          {
            "type":"SourceInfo",
            "node":{
              "type":"XmlTextNode",
              "contents":"This question's answer tends to change over time... I'd like to know the current status of Netty 4. What does &quot;CR2&quot; stand for? &quot;Candidate for Release 2&quot;? It seems that the Netty 4 api is improved in comparison to Netty 3, but then again, how stable is it?"
            },
            "units":[
              {
                "type":"TextUnit",
                "id":"[10210368-cu23754340]-[770905741]",
                "astNode":{
                  "type":"TextFragmentNode",
                  "text":"This question's answer tends to change over time... I'd like to know the current status of Netty 4. What does &quot;CR2&quot; stand for? &quot;Candidate for Release 2&quot;? It seems that the Netty 4 api is improved in comparison to Netty 3, but then again, how stable is it?"
                },
                "codeFragments":{
                  "type":"CodeFragmentSequence",
                  "fragments":[
                    
                  ]
                },
                "metaInformation":[
                  {
                    "type":"NaturalLanguageMetaInformation",
                    "tfMap":{
                      "chang":1,
                      "question":1,
                      "comparison":1,
                      "stabl":1,
                      "stand":1,
                      "improv":1,
                      "candid":1,
                      "releas":1,
                      "status":1,
                      "answer":1,
                      "quot":4,
                      "api":1,
                      "time":1,
                      "current":1,
                      "netti":3
                    }
                  },
                  {
                    "type":"CodeTypesMetaInformation",
                    "qualifiedTypes":[
                      
                    ],
                    "simpleTypes":[
                      
                    ],
                    "basicTypes":[
                      
                    ]
                  },
                  {
                    "type":"CodeInvocationMetaInformation",
                    "invocations":[
                      
                    ]
                  },
                  {
                    "type":"CodeVariablesMetaInformation",
                    "variables":[
                      
                    ]
                  }
                ]
              }
            ]
          }
        ]
      }
    ],
    "tags":[
      "java",
      "netty"
    ],
    "creationDate":"2012-04-18",
    "lastActivityDate":"2012-04-29",
    "lastEditDate":"2012-04-29",
    "score":5,
    "viewCount":2087,
    "owner":{
      "type":"StackOverflowUser",
      "id":1341438,
      "displayName":"Keith",
      "reputation":36
    },
    "source":[
      {
        "type":"SourceInfo",
        "node":{
          "type":"XmlTextNode",
          "contents":"<p>How stable is Netty 4, at least the parts that implement the HTTP codec, including web sockets? Is that portion just a renaming of packages, or have there been some fundamental architectural changes that make the code unstable?</p>"
        },
        "units":[
          {
            "type":"TextUnit",
            "id":"[10210368]-[1361776688]",
            "astNode":{
              "type":"TextFragmentNode",
              "text":"<p>How stable is Netty 4, at least the parts that implement the HTTP codec, including web sockets? Is that portion just a renaming of packages, or have there been some fundamental architectural changes that make the code unstable?</p>"
            },
            "codeFragments":{
              "type":"CodeFragmentSequence",
              "fragments":[
                
              ]
            },
            "metaInformation":[
              {
                "type":"NaturalLanguageMetaInformation",
                "tfMap":{
                  "portion":1,
                  "socket":1,
                  "unstabl":1,
                  "stabl":1,
                  "renam":1,
                  "includ":1,
                  "code":1,
                  "web":1,
                  "architectur":1,
                  "implement":1,
                  "make":1,
                  "codec":1,
                  "packag":1,
                  "part":1,
                  "netti":1,
                  "http":1,
                  "fundament":1
                }
              },
              {
                "type":"CodeTypesMetaInformation",
                "qualifiedTypes":[
                  
                ],
                "simpleTypes":[
                  
                ],
                "basicTypes":[
                  
                ]
              },
              {
                "type":"CodeInvocationMetaInformation",
                "invocations":[
                  
                ]
              },
              {
                "type":"CodeVariablesMetaInformation",
                "variables":[
                  
                ]
              }
            ]
          }
        ]
      },
      {
        "type":"SourceInfo",
        "node":{
          "type":"XmlTextNode",
          "contents":"<p>I need to be able to use the HttpPost functionality from 4. I thought about trying to make it run in 3.4.0, but I am using OpenJDK and trying to drop 3.4.0 in gave me a stack trace because it couldn't load the class sun.misc.Unsafe. Perhaps this had something to do with trying to run this in an OSGi container, but I also looked at the rt.jar file in my OpenJDK install and sun.misc.Unsafe wasn't there. Perhaps just building it and making the sun.misc classes optional in the OSGi headers would help.</p>"
        },
        "units":[
          {
            "type":"TextUnit",
            "id":"[10210368]-[9855338]",
            "astNode":{
              "type":"TextFragmentNode",
              "text":"<p>I need to be able to use the HttpPost functionality from 4. I thought about trying to make it run in 3.4.0, but I am using OpenJDK and trying to drop 3.4.0 in gave me a stack trace because it couldn't load the class sun.misc.Unsafe. Perhaps this had something to do with trying to run this in an OSGi container, but I also looked at the rt.jar file in my OpenJDK install and sun.misc.Unsafe wasn't there. Perhaps just building it and making the sun.misc classes optional in the OSGi headers would help.</p>"
            },
            "codeFragments":{
              "type":"CodeFragmentSequence",
              "fragments":[
                {
                  "type":"ReferenceTypeNode",
                  "ids":[
                    {
                      "type":"ParameterizedTypeNode",
                      "identifier":{
                        "type":"IdentifierNode",
                        "name":"HttpPost",
                        "comments":[
                          
                        ]
                      },
                      "comments":[
                        
                      ]
                    }
                  ],
                  "comments":[
                    
                  ]
                },
                {
                  "type":"ClassDeclarationNode",
                  "modifiers":[
                    
                  ],
                  "identifier":{
                    "type":"IdentifierNode",
                    "name":"sun",
                    "comments":[
                      
                    ]
                  },
                  "labels":[
                    
                  ],
                  "comments":[
                    
                  ]
                },
                {
                  "type":"ReferenceTypeNode",
                  "ids":[
                    {
                      "type":"ParameterizedTypeNode",
                      "identifier":{
                        "type":"IdentifierNode",
                        "name":"sun",
                        "comments":[
                          
                        ]
                      },
                      "comments":[
                        
                      ]
                    },
                    {
                      "type":"ParameterizedTypeNode",
                      "identifier":{
                        "type":"IdentifierNode",
                        "name":"misc",
                        "comments":[
                          
                        ]
                      },
                      "comments":[
                        
                      ]
                    },
                    {
                      "type":"ParameterizedTypeNode",
                      "identifier":{
                        "type":"IdentifierNode",
                        "name":"Unsafe",
                        "comments":[
                          
                        ]
                      },
                      "comments":[
                        
                      ]
                    }
                  ],
                  "comments":[
                    
                  ]
                }
              ]
            },
            "metaInformation":[
              {
                "type":"NaturalLanguageMetaInformation",
                "tfMap":{
                  "post":1,
                  "trace":1,
                  "thought":1,
                  "run":2,
                  "look":1,
                  "sun":3,
                  "option":1,
                  "build":1,
                  "load":1,
                  "wasn":1,
                  "contain":1,
                  "open":2,
                  "drop":1,
                  "instal":1,
                  "function":1,
                  "gave":1,
                  "stack":1,
                  "misc":3,
                  "make":2,
                  "header":1,
                  "class":1,
                  "file":1,
                  "unsaf":2,
                  "http":1,
                  "jar":1,
                  "jdk":2,
                  "osgi":2
                }
              },
              {
                "type":"CodeTypesMetaInformation",
                "qualifiedTypes":[
                  {
                    "type":"ReferenceTypeNode",
                    "ids":[
                      {
                        "type":"ParameterizedTypeNode",
                        "identifier":{
                          "type":"IdentifierNode",
                          "name":"sun",
                          "comments":[
                            
                          ]
                        },
                        "comments":[
                          
                        ]
                      },
                      {
                        "type":"ParameterizedTypeNode",
                        "identifier":{
                          "type":"IdentifierNode",
                          "name":"misc",
                          "comments":[
                            
                          ]
                        },
                        "comments":[
                          
                        ]
                      },
                      {
                        "type":"ParameterizedTypeNode",
                        "identifier":{
                          "type":"IdentifierNode",
                          "name":"Unsafe",
                          "comments":[
                            
                          ]
                        },
                        "comments":[
                          
                        ]
                      }
                    ],
                    "comments":[
                      
                    ]
                  }
                ],
                "simpleTypes":[
                  {
                    "type":"ReferenceTypeNode",
                    "ids":[
                      {
                        "type":"ParameterizedTypeNode",
                        "identifier":{
                          "type":"IdentifierNode",
                          "name":"HttpPost",
                          "comments":[
                            
                          ]
                        },
                        "comments":[
                          
                        ]
                      }
                    ],
                    "comments":[
                      
                    ]
                  }
                ],
                "basicTypes":[
                  
                ]
              },
              {
                "type":"CodeInvocationMetaInformation",
                "invocations":[
                  
                ]
              },
              {
                "type":"CodeVariablesMetaInformation",
                "variables":[
                  
                ]
              }
            ]
          }
        ]
      },
      {
        "type":"SourceInfo",
        "node":{
          "type":"XmlTextNode",
          "contents":"<p>Using the Sun VM is not an option here, I need to use OpenJDK.</p>"
        },
        "units":[
          {
            "type":"TextUnit",
            "id":"[10210368]-[1290129298]",
            "astNode":{
              "type":"TextFragmentNode",
              "text":"<p>Using the Sun VM is not an option here, I need to use OpenJDK.</p>"
            },
            "codeFragments":{
              "type":"CodeFragmentSequence",
              "fragments":[
                
              ]
            },
            "metaInformation":[
              {
                "type":"NaturalLanguageMetaInformation",
                "tfMap":{
                  "sun":1,
                  "jdk":1,
                  "open":1,
                  "option":1
                }
              },
              {
                "type":"CodeTypesMetaInformation",
                "qualifiedTypes":[
                  
                ],
                "simpleTypes":[
                  
                ],
                "basicTypes":[
                  
                ]
              },
              {
                "type":"CodeInvocationMetaInformation",
                "invocations":[
                  
                ]
              },
              {
                "type":"CodeVariablesMetaInformation",
                "variables":[
                  
                ]
              }
            ]
          }
        ]
      }
    ]
  },
  "answers":[
    {
      "type":"StackOverflowAnswer",
      "id":10215836,
      "questionId":10210368,
      "comments":[
        {
          "type":"StackOverflowComment",
          "id":13129791,
          "postId":10215836,
          "creationDate":"2012-04-19",
          "score":0,
          "isEdited":false,
          "owner":{
            "type":"StackOverflowUser",
            "id":827310,
            "displayName":"Ngoc Dao",
            "reputation":748
          },
          "source":[
            {
              "type":"SourceInfo",
              "node":{
                "type":"XmlTextNode",
                "contents":"Good to hear about 3.5.0.Final. When will it be released? Does it include file upload? File upload is the only reason I am using Netty 4 for Xitrum (https://github.com/ngocdaothanh/xitrum)."
              },
              "units":[
                {
                  "type":"TextUnit",
                  "id":"[10215836-cu13129791]-[639854053]",
                  "astNode":{
                    "type":"TextFragmentNode",
                    "text":"Good to hear about 3.5.0.Final. When will it be released? Does it include file upload? File upload is the only reason I am using Netty 4 for Xitrum (https://github.com/ngocdaothanh/xitrum)."
                  },
                  "codeFragments":{
                    "type":"CodeFragmentSequence",
                    "fragments":[
                      
                    ]
                  },
                  "metaInformation":[
                    {
                      "type":"NaturalLanguageMetaInformation",
                      "tfMap":{
                        "github":1,
                        "ngocdaothanh":1,
                        "good":1,
                        "https":1,
                        "reason":1,
                        "hear":1,
                        "includ":1,
                        "releas":1,
                        "upload":2,
                        "xitrum":2,
                        "file":2,
                        "netti":1
                      }
                    },
                    {
                      "type":"CodeTypesMetaInformation",
                      "qualifiedTypes":[
                        
                      ],
                      "simpleTypes":[
                        
                      ],
                      "basicTypes":[
                        
                      ]
                    },
                    {
                      "type":"CodeInvocationMetaInformation",
                      "invocations":[
                        
                      ]
                    },
                    {
                      "type":"CodeVariablesMetaInformation",
                      "variables":[
                        
                      ]
                    }
                  ]
                }
              ]
            }
          ]
        },
        {
          "type":"StackOverflowComment",
          "id":13124691,
          "postId":10215836,
          "creationDate":"2012-04-18",
          "score":0,
          "isEdited":false,
          "owner":{
            "type":"StackOverflowUser",
            "id":1341438,
            "displayName":"Keith",
            "reputation":36
          },
          "source":[
            {
              "type":"SourceInfo",
              "node":{
                "type":"XmlTextNode",
                "contents":"OK, many thanks. I am comfortable with fixing things, though it depends on what exactly you are breaking. Is it just how things are being called, or is it that a lot of functionality just doesn't work?. I will wait for 3.4.1 to update. Any idea on 3.5.0 timeline?"
              },
              "units":[
                {
                  "type":"TextUnit",
                  "id":"[10215836-cu13124691]-[1504281139]",
                  "astNode":{
                    "type":"TextFragmentNode",
                    "text":"OK, many thanks. I am comfortable with fixing things, though it depends on what exactly you are breaking. Is it just how things are being called, or is it that a lot of functionality just doesn't work?. I will wait for 3.4.1 to update. Any idea on 3.5.0 timeline?"
                  },
                  "codeFragments":{
                    "type":"CodeFragmentSequence",
                    "fragments":[
                      
                    ]
                  },
                  "metaInformation":[
                    {
                      "type":"NaturalLanguageMetaInformation",
                      "tfMap":{
                        "wait":1,
                        "break":1,
                        "depend":1,
                        "timelin":1,
                        "idea":1,
                        "updat":1,
                        "fix":1,
                        "thing":2,
                        "comfort":1,
                        "work":1,
                        "function":1,
                        "lot":1,
                        "call":1
                      }
                    },
                    {
                      "type":"CodeTypesMetaInformation",
                      "qualifiedTypes":[
                        
                      ],
                      "simpleTypes":[
                        
                      ],
                      "basicTypes":[
                        
                      ]
                    },
                    {
                      "type":"CodeInvocationMetaInformation",
                      "invocations":[
                        
                      ]
                    },
                    {
                      "type":"CodeVariablesMetaInformation",
                      "variables":[
                        
                      ]
                    }
                  ]
                }
              ]
            }
          ]
        },
        {
          "type":"StackOverflowComment",
          "id":13132941,
          "postId":10215836,
          "creationDate":"2012-04-19",
          "score":0,
          "isEdited":false,
          "owner":{
            "type":"StackOverflowUser",
            "id":1074097,
            "displayName":"Norman Maurer",
            "reputation":9027
          },
          "source":[
            {
              "type":"SourceInfo",
              "node":{
                "type":"XmlTextNode",
                "contents":"@ngocdaothanh yeah it should be also part of 3.5.x"
              },
              "units":[
                {
                  "type":"TextUnit",
                  "id":"[10215836-cu13132941]-[1730301861]",
                  "astNode":{
                    "type":"TextFragmentNode",
                    "text":"@ngocdaothanh yeah it should be also part of 3.5.x"
                  },
                  "codeFragments":{
                    "type":"CodeFragmentSequence",
                    "fragments":[
                      
                    ]
                  },
                  "metaInformation":[
                    {
                      "type":"NaturalLanguageMetaInformation",
                      "tfMap":{
                        "ngocdaothanh":1,
                        "part":1,
                        "yeah":1
                      }
                    },
                    {
                      "type":"CodeTypesMetaInformation",
                      "qualifiedTypes":[
                        
                      ],
                      "simpleTypes":[
                        
                      ],
                      "basicTypes":[
                        
                      ]
                    },
                    {
                      "type":"CodeInvocationMetaInformation",
                      "invocations":[
                        
                      ]
                    },
                    {
                      "type":"CodeVariablesMetaInformation",
                      "variables":[
                        
                      ]
                    }
                  ]
                }
              ]
            }
          ]
        },
        {
          "type":"StackOverflowComment",
          "id":13132966,
          "postId":10215836,
          "creationDate":"2012-04-19",
          "score":0,
          "isEdited":false,
          "owner":{
            "type":"StackOverflowUser",
            "id":1074097,
            "displayName":"Norman Maurer",
            "reputation":9027
          },
          "source":[
            {
              "type":"SourceInfo",
              "node":{
                "type":"XmlTextNode",
                "contents":"@user1341438 wewill break the handler api and many more. So I'm talking about big changes... After 4.0.0.Alpha1 it should be more stable. There is no timeline fixed yet but I would expect it to be out soon after 3.4.1.Final is out"
              },
              "units":[
                {
                  "type":"TextUnit",
                  "id":"[10215836-cu13132966]-[-400698395]",
                  "astNode":{
                    "type":"TextFragmentNode",
                    "text":"@user1341438 wewill break the handler api and many more. So I'm talking about big changes... After 4.0.0.Alpha1 it should be more stable. There is no timeline fixed yet but I would expect it to be out soon after 3.4.1.Final is out"
                  },
                  "codeFragments":{
                    "type":"CodeFragmentSequence",
                    "fragments":[
                      
                    ]
                  },
                  "metaInformation":[
                    {
                      "type":"NaturalLanguageMetaInformation",
                      "tfMap":{
                        "alpha":1,
                        "big":1,
                        "timelin":1,
                        "fix":1,
                        "stabl":1,
                        "talk":1,
                        "expect":1,
                        "wewil":1,
                        "api":1,
                        "handler":1,
                        "user":1
                      }
                    },
                    {
                      "type":"CodeTypesMetaInformation",
                      "qualifiedTypes":[
                        
                      ],
                      "simpleTypes":[
                        
                      ],
                      "basicTypes":[
                        
                      ]
                    },
                    {
                      "type":"CodeInvocationMetaInformation",
                      "invocations":[
                        
                      ]
                    },
                    {
                      "type":"CodeVariablesMetaInformation",
                      "variables":[
                        
                      ]
                    }
                  ]
                }
              ]
            }
          ]
        },
        {
          "type":"StackOverflowComment",
          "id":13555963,
          "postId":10215836,
          "creationDate":"2012-05-07",
          "score":0,
          "isEdited":false,
          "owner":{
            "type":"StackOverflowUser",
            "id":1074097,
            "displayName":"Norman Maurer",
            "reputation":9027
          },
          "source":[
            {
              "type":"SourceInfo",
              "node":{
                "type":"XmlTextNode",
                "contents":"The 3 branch should have it"
              },
              "units":[
                {
                  "type":"TextUnit",
                  "id":"[10215836-cu13555963]-[435880120]",
                  "astNode":{
                    "type":"TextFragmentNode",
                    "text":"The 3 branch should have it"
                  },
                  "codeFragments":{
                    "type":"CodeFragmentSequence",
                    "fragments":[
                      
                    ]
                  },
                  "metaInformation":[
                    {
                      "type":"NaturalLanguageMetaInformation",
                      "tfMap":{
                        "branch":1
                      }
                    },
                    {
                      "type":"CodeTypesMetaInformation",
                      "qualifiedTypes":[
                        
                      ],
                      "simpleTypes":[
                        
                      ],
                      "basicTypes":[
                        
                      ]
                    },
                    {
                      "type":"CodeInvocationMetaInformation",
                      "invocations":[
                        
                      ]
                    },
                    {
                      "type":"CodeVariablesMetaInformation",
                      "variables":[
                        
                      ]
                    }
                  ]
                }
              ]
            }
          ]
        },
        {
          "type":"StackOverflowComment",
          "id":13558546,
          "postId":10215836,
          "creationDate":"2012-05-07",
          "score":0,
          "isEdited":false,
          "owner":{
            "type":"StackOverflowUser",
            "id":1341438,
            "displayName":"Keith",
            "reputation":36
          },
          "source":[
            {
              "type":"SourceInfo",
              "node":{
                "type":"XmlTextNode",
                "contents":"Got it, all compiled and everything. Many thanks!"
              },
              "units":[
                {
                  "type":"TextUnit",
                  "id":"[10215836-cu13558546]-[-1416787870]",
                  "astNode":{
                    "type":"TextFragmentNode",
                    "text":"Got it, all compiled and everything. Many thanks!"
                  },
                  "codeFragments":{
                    "type":"CodeFragmentSequence",
                    "fragments":[
                      
                    ]
                  },
                  "metaInformation":[
                    {
                      "type":"NaturalLanguageMetaInformation",
                      "tfMap":{
                        "compil":1
                      }
                    },
                    {
                      "type":"CodeTypesMetaInformation",
                      "qualifiedTypes":[
                        
                      ],
                      "simpleTypes":[
                        
                      ],
                      "basicTypes":[
                        
                      ]
                    },
                    {
                      "type":"CodeInvocationMetaInformation",
                      "invocations":[
                        
                      ]
                    },
                    {
                      "type":"CodeVariablesMetaInformation",
                      "variables":[
                        
                      ]
                    }
                  ]
                }
              ]
            }
          ]
        },
        {
          "type":"StackOverflowComment",
          "id":13555193,
          "postId":10215836,
          "creationDate":"2012-05-07",
          "score":0,
          "isEdited":false,
          "owner":{
            "type":"StackOverflowUser",
            "id":1341438,
            "displayName":"Keith",
            "reputation":36
          },
          "source":[
            {
              "type":"SourceInfo",
              "node":{
                "type":"XmlTextNode",
                "contents":"So if I want the file Upload, should I build off of the master branch at this point? Or should I go with the 3.5 branch, and, if so, where is that? All of the branches I found with the org.jboss package didn't have the file upload, only the io.netty."
              },
              "units":[
                {
                  "type":"TextUnit",
                  "id":"[10215836-cu13555193]-[1588979371]",
                  "astNode":{
                    "type":"TextFragmentNode",
                    "text":"So if I want the file Upload, should I build off of the master branch at this point? Or should I go with the 3.5 branch, and, if so, where is that? All of the branches I found with the org.jboss package didn't have the file upload, only the io.netty."
                  },
                  "codeFragments":{
                    "type":"CodeFragmentSequence",
                    "fragments":[
                      
                    ]
                  },
                  "metaInformation":[
                    {
                      "type":"NaturalLanguageMetaInformation",
                      "tfMap":{
                        "point":1,
                        "master":1,
                        "branch":3,
                        "build":1,
                        "found":1,
                        "jboss":1,
                        "upload":2,
                        "file":2,
                        "org":1,
                        "netti":1
                      }
                    },
                    {
                      "type":"CodeTypesMetaInformation",
                      "qualifiedTypes":[
                        
                      ],
                      "simpleTypes":[
                        
                      ],
                      "basicTypes":[
                        
                      ]
                    },
                    {
                      "type":"CodeInvocationMetaInformation",
                      "invocations":[
                        
                      ]
                    },
                    {
                      "type":"CodeVariablesMetaInformation",
                      "variables":[
                        
                      ]
                    }
                  ]
                }
              ]
            }
          ]
        }
      ],
      "creationDate":"2012-04-18",
      "lastActivityDate":"2012-04-29",
      "lastEditDate":"2012-04-29",
      "score":4,
      "isAccepted":false,
      "owner":{
        "type":"StackOverflowUser",
        "id":1074097,
        "displayName":"Norman Maurer",
        "reputation":9027
      },
      "source":[
        {
          "type":"SourceInfo",
          "node":{
            "type":"XmlTextNode",
            "contents":"<p>Netty 4.x is not really stable yet. We will prolly break a lot of the API within the next weeks. So unless you know what you do I would not use it yet ;)</p>"
          },
          "units":[
            {
              "type":"TextUnit",
              "id":"[10215836]-[2024603602]",
              "astNode":{
                "type":"TextFragmentNode",
                "text":"<p>Netty 4.x is not really stable yet. We will prolly break a lot of the API within the next weeks. So unless you know what you do I would not use it yet ;)</p>"
              },
              "codeFragments":{
                "type":"CodeFragmentSequence",
                "fragments":[
                  
                ]
              },
              "metaInformation":[
                {
                  "type":"NaturalLanguageMetaInformation",
                  "tfMap":{
                    "prolli":1,
                    "stabl":1,
                    "week":1,
                    "lot":1,
                    "api":1,
                    "netti":1
                  }
                },
                {
                  "type":"CodeTypesMetaInformation",
                  "qualifiedTypes":[
                    
                  ],
                  "simpleTypes":[
                    
                  ],
                  "basicTypes":[
                    
                  ]
                },
                {
                  "type":"CodeInvocationMetaInformation",
                  "invocations":[
                    
                  ]
                },
                {
                  "type":"CodeVariablesMetaInformation",
                  "variables":[
                    
                  ]
                }
              ]
            }
          ]
        },
        {
          "type":"SourceInfo",
          "node":{
            "type":"XmlTextNode",
            "contents":"<p>The problem with the Unsafe class should be fixed in 3.4.1.Final which should be out this week if everything works out. The fix is related to <a href=\"https://github.com/netty/netty/issues/268\"rel=\"nofollow\">this</a>.</p>"
          },
          "units":[
            {
              "type":"TextUnit",
              "id":"[10215836]-[-142302134]",
              "astNode":{
                "type":"TextFragmentNode",
                "text":"<p>The problem with the Unsafe class should be fixed in 3.4.1.Final which should be out this week if everything works out. The fix is related to <a href=\"https://github.com/netty/netty/issues/268\"rel=\"nofollow\">this</a>.</p>"
              },
              "codeFragments":{
                "type":"CodeFragmentSequence",
                "fragments":[
                  {
                    "type":"ClassDeclarationNode",
                    "modifiers":[
                      
                    ],
                    "identifier":{
                      "type":"IdentifierNode",
                      "name":"should",
                      "comments":[
                        
                      ]
                    },
                    "labels":[
                      
                    ],
                    "comments":[
                      
                    ]
                  }
                ]
              },
              "metaInformation":[
                {
                  "type":"NaturalLanguageMetaInformation",
                  "tfMap":{
                    "github":1,
                    "relat":1,
                    "problem":1,
                    "fix":2,
                    "rel":1,
                    "issu":1,
                    "https":1,
                    "work":1,
                    "week":1,
                    "nofollow":1,
                    "unsaf":1,
                    "href":1,
                    "netti":2
                  }
                },
                {
                  "type":"CodeTypesMetaInformation",
                  "qualifiedTypes":[
                    
                  ],
                  "simpleTypes":[
                    
                  ],
                  "basicTypes":[
                    
                  ]
                },
                {
                  "type":"CodeInvocationMetaInformation",
                  "invocations":[
                    
                  ]
                },
                {
                  "type":"CodeVariablesMetaInformation",
                  "variables":[
                    
                  ]
                }
              ]
            }
          ]
        },
        {
          "type":"SourceInfo",
          "node":{
            "type":"XmlTextNode",
            "contents":"<p>We plan to have a 3.5.0.Final release which will include the HttpPost stuff. We just want to have 3.4.1.Final first. So stay tuned..</p>"
          },
          "units":[
            {
              "type":"TextUnit",
              "id":"[10215836]-[-290166885]",
              "astNode":{
                "type":"TextFragmentNode",
                "text":"<p>We plan to have a 3.5.0.Final release which will include the HttpPost stuff. We just want to have 3.4.1.Final first. So stay tuned..</p>"
              },
              "codeFragments":{
                "type":"CodeFragmentSequence",
                "fragments":[
                  {
                    "type":"ReferenceTypeNode",
                    "ids":[
                      {
                        "type":"ParameterizedTypeNode",
                        "identifier":{
                          "type":"IdentifierNode",
                          "name":"HttpPost",
                          "comments":[
                            
                          ]
                        },
                        "comments":[
                          
                        ]
                      }
                    ],
                    "comments":[
                      
                    ]
                  }
                ]
              },
              "metaInformation":[
                {
                  "type":"NaturalLanguageMetaInformation",
                  "tfMap":{
                    "tune":1,
                    "post":1,
                    "includ":1,
                    "releas":1,
                    "stuff":1,
                    "stay":1,
                    "http":1,
                    "plan":1
                  }
                },
                {
                  "type":"CodeTypesMetaInformation",
                  "qualifiedTypes":[
                    
                  ],
                  "simpleTypes":[
                    {
                      "type":"ReferenceTypeNode",
                      "ids":[
                        {
                          "type":"ParameterizedTypeNode",
                          "identifier":{
                            "type":"IdentifierNode",
                            "name":"HttpPost",
                            "comments":[
                              
                            ]
                          },
                          "comments":[
                            
                          ]
                        }
                      ],
                      "comments":[
                        
                      ]
                    }
                  ],
                  "basicTypes":[
                    
                  ]
                },
                {
                  "type":"CodeInvocationMetaInformation",
                  "invocations":[
                    
                  ]
                },
                {
                  "type":"CodeVariablesMetaInformation",
                  "variables":[
                    
                  ]
                }
              ]
            }
          ]
        }
      ]
    }
  ]
}